mzfit/__init__.py
mzfit/core.py
mzfit-0.1.dist-info/LICENSE
mzfit-0.1.dist-info/METADATA
mzfit-0.1.dist-info/WHEEL
mzfit-0.1.dist-info/top_level.txt
mzfit-0.1.dist-info/RECORD
