Metadata-Version: 2.1
Name: mzfit
Version: 0.1
Summary: zfit wrapper for lazy analysts
Home-page: https://github.com/mzks/mzfit
Author: Keita Mizukoshi
Author-email: mzks@stu.kobe-u.ac.jp
Maintainer: Keita Mizukoshi
Maintainer-email: mzks@stu.kobe-u.ac.jp
License: MIT
Platform: UNKNOWN
Classifier: Programming Language :: Python :: 3
Classifier: License :: OSI Approved :: MIT License
Requires-Python: >=3.7
Requires-Dist: numpy
Requires-Dist: matplotlib
Requires-Dist: zfit
